{
    "jobId": "f2c8497d-3559-4ce8-a549-55a94d12090a",
    "status": 2,
    "joinScriptUrl": "https://assetgame.roblox.com/Game/Join.ashx?ticketVersion=2&ticket=%7b%22UserId%22%3a245288101%2c%22UserName%22%3a%22ChristineHerrera41%22%2c%22DisplayName%22%3a%22ChristineHerrera41%22%2c%22CharacterFetchUrl%22%3a%22https%3a%2f%2fapi.roblox.com%2fv1.1%2favatar-fetch%2f%3fplaceId%3d4483381587%26userId%3d245288101%22%2c%22GameId%22%3a%22f2c8497d-3559-4ce8-a549-55a94d12090a%22%2c%22PlaceId%22%3a4483381587%2c%22UniverseId%22%3a1430993116%2c%22ServerId%22%3a121021%2c%22ServerPort%22%3a65091%2c%22IsTeleport%22%3afalse%2c%22FollowUserId%22%3anull%2c%22TimeStamp%22%3a%229%2f30%2f2022+4%3a41%3a24+AM%22%2c%22CharacterAppearanceId%22%3a245288101%2c%22AlternateName%22%3anull%2c%22JoinTypeId%22%3a5%2c%22MatchmakingDecisionId%22%3anull%2c%22GameJoinMetadata%22%3a%7b%22JoinSource%22%3a0%2c%22RequestType%22%3a0%2c%22MatchmakingDecisionId%22%3a%2200000000-0000-0000-0000-000000000000%22%2c%22IsPlaceVoiceChatEnabled%22%3afalse%7d%2c%22SourcePlaceId%22%3anull%7d&signature=NNW7sLJKTbx3O8OK2hRBuHaAPFEPGVDy%2fLy7ZtMPn0IHRF6huXA5pR%2fEeXF%2b0bHa0BrMxO4%2fbe4ByOGveXcE%2fCu1zOnzeGLRAn6EYZ5aoCaATgHAU936wsblePn3KZ73zbW7QpEeQCwxIRzGpBsrEAHPRczCV5VrqJl%2bs91gGZZwsUu02JwwwOHz1uLXgyWYkxBze0KZ2Ssoi0tXhgWg7kM6h1mu%2bMcI2WgsG%2bcYub2WU5SSlCZDtfgS9%2bp6hBEJOKx5VojSdN61ZDYcgB1%2feudLl%2fD3lYTc6Jko4Y%2f5fgfUBwq6tY%2fR9uz7jji2Md9CqGauGuzmYYVlw%2fB%2fzeVFew%3d%3d&browserTrackerId=0",
    "authenticationUrl": "",
    "authenticationTicket": "",
    "message": null,
    "joinScript": {
      "ClientPort": 0,
      "MachineAddress": "128.116.74.137",
      "ServerPort": 65091,
      "ServerConnections": [
        {
          "Address": "128.116.74.137",
          "Port": 65091
        }
      ],
      "DirectServerReturn": true,
      "PingUrl": "https://assetgame.roblox.com/Game/ClientPresence.ashx?version=old&PlaceID=4483381587&GameID=f2c8497d-3559-4ce8-a549-55a94d12090a&UserID=245288101",
      "PingInterval": 120,
      "UserName": "This is ur lego username",
      "DisplayName": "This is ur lego display name",
      "SeleniumTestMode": false,
      "UserId": 245288101,
      "RobloxLocale": "en_us",
      "GameLocale": "en_us",
      "SuperSafeChat": false,
      "FlexibleChatEnabled": false,
      "CharacterAppearance": "https://api.roblox.com/v1.1/avatar-fetch/?placeId=4483381587&userId=245288101",
      "ClientTicket": "THERES SOME ENCODED DATA IN HERE;6",
      "GameId": "f2c8497d-3559-4ce8-a549-55a94d12090a",
      "PlaceId": 4483381587,
      "BaseUrl": "http://gamejoin.roblox.com/",
      "ChatStyle": "Classic",
      "CreatorId": 157644,
      "CreatorTypeEnum": "User",
      "MembershipType": "None",
      "AccountAge": 2047,
      "CookieStoreFirstTimePlayKey": "rbx_evt_ftp",
      "CookieStoreFiveMinutePlayKey": "rbx_evt_fmp",
      "CookieStoreEnabled": true,
      "IsUnknownOrUnder13": false,
      "GameChatType": "AllUsers",
      "SessionId": "{\"SessionId\":\"bbec9b40-05da-4c06-8664-06f263e92641\",\"GameId\":\"f2c8497d-3559-4ce8-a549-55a94d12090a\",\"PlaceId\":4483381587,\"ClientIpAddress\":\"They logging ur ip\",\"PlatformTypeId\":5,\"SessionStarted\":\"2022-09-30T09:41:24.3145318Z\",\"BrowserTrackerId\":0,\"PartyId\":null,\"Age\":80.783560352760659,\"Latitude\":Ur Latitude,\"Longitude\":Ur Longitude,\"CountryId\":Ur country code,\"PolicyCountryId\":null,\"LanguageId\":Yep,\"BlockedPlayerIds\":[],\"JoinType\":\"Specific\",\"PlaySessionFlags\":0,\"MatchmakingDecisionId\":null,\"GameJoinMetadata\":{\"JoinSource\":0,\"RequestType\":0},\"RandomSeed2\":\"A seed\",\"IsUserVoiceChatEnabled\":pretty sure this can be spoofed,\"SourcePlaceId\":null}",
      "AnalyticsSessionId": "bbec9b40-05da-4c06-8664-06f263e92641",
      "DataCenterId": 299,
      "UniverseId": 1430993116,
      "FollowUserId": 0,
      "characterAppearanceId": 245288101,
      "CountryCode": "RO",
      "RandomSeed1": "6pVS9ADvivchxzCoM86+jPKn71r0EVKm7VxApzeH20mJpsXZ81xzDWvKD4xianRS+Vrh0JaZZpSm+bIyR6bIoQ==",
      "ClientPublicKeyData": "{\"creationTime\":\"19:56 11/23/2021\",\"applications\":{\"RakNetEarlyPublicKey\":{\"versions\":[{\"id\":2,\"value\":\"Another stuff here\",\"allowed\":true}],\"send\":2,\"revert\":2}}}",
      "RccVersion": "0.546.0.5460521",
      "ChannelName": ""
    }
  }